common_stats/__init__.py
common_stats/statistics.py
common_stats_test-0.0.2.dist-info/LICENSE
common_stats_test-0.0.2.dist-info/METADATA
common_stats_test-0.0.2.dist-info/WHEEL
common_stats_test-0.0.2.dist-info/top_level.txt
common_stats_test-0.0.2.dist-info/RECORD
