Metadata-Version: 2.1
Name: common-stats-test
Version: 0.0.2
Summary: A simple library for basic statistical calculations
Author: Tommy Chang
Author-email: techang1710@email.com
License: MIT
Requires-Python: >=3.7
License-File: LICENSE
Requires-Dist: pytest
